encryption/__init__.py
encryption/encryption.py
pycryto-0.1.0.dist-info/METADATA
pycryto-0.1.0.dist-info/WHEEL
pycryto-0.1.0.dist-info/top_level.txt
pycryto-0.1.0.dist-info/RECORD
