Metadata-Version: 2.1
Name: pycryto
Version: 0.1.0
Summary: A simple cryptography library using AES and PKCS7 padding
Home-page: https://github.com/yourusername/pycryto
Author: ZSU
Author-email: 
Classifier: Programming Language :: Python :: 3
Classifier: License :: OSI Approved :: MIT License
Classifier: Operating System :: OS Independent
Requires-Python: >=3.6
Requires-Dist: cryptography
